[{"id":"16e849247857","url":"","urloption":"hidden","projectstatus":"bg-red-600","imagelow":"assets/image/low/post/44151b555d6db75cfb8becf97ff9e07b.jpeg","imagehigh":"assets/image/high/post/44151b555d6db75cfb8becf97ff9e07b.jpeg","content":"Another new long-bar version of `oodoo` laptop cooling stand. It has 24 cm long, 16 rolls and nicely fit for 14 inches laptop.","date":"4 Jun 2018"},{"id":"c1ac7c6a1268","url":"","urloption":"hidden","projectstatus":"bg-red-600","imagelow":"assets/image/low/post/699a351469bcda78f6a4788203ab54aa.jpeg","imagehigh":"assets/image/high/post/699a351469bcda78f6a4788203ab54aa.jpeg","content":"My homemade creative laptop stand that has 2 spiral-rolling suspensions in the concept design. Very long-lasting, very robust, the design is minimalist and simple to be recreated with any similar nilon type material.","date":"4 Jun 2018"}]